ropt_dakota/__init__.py
ropt_dakota/dakota.py
ropt_dakota/py.typed
ropt_dakota/version.py
ropt_dakota-0.24.1.dist-info/licenses/LICENSE
ropt_dakota-0.24.1.dist-info/METADATA
ropt_dakota-0.24.1.dist-info/WHEEL
ropt_dakota-0.24.1.dist-info/entry_points.txt
ropt_dakota-0.24.1.dist-info/top_level.txt
ropt_dakota-0.24.1.dist-info/RECORD
