Metadata-Version: 2.4
Name: ropt-dakota
Version: 0.24.1
Summary: A Dakota optimizer plugin for ropt
Project-URL: Homepage, https://github.com/TNO-ropt/ropt-dakota
Project-URL: Repository, https://github.com/TNO-ropt/ropt-dakota
Project-URL: Bug Tracker, https://github.com/TNO-ropt/ropt-dakota/issues
Classifier: Development Status :: 4 - Beta
Classifier: License :: OSI Approved :: GNU General Public License v3 (GPLv3)
Classifier: Natural Language :: English
Classifier: Programming Language :: Python
Classifier: Programming Language :: Python :: 3.11
Classifier: Programming Language :: Python :: 3.12
Classifier: Programming Language :: Python :: 3.13
Classifier: Topic :: Scientific/Engineering
Requires-Python: >=3.11
License-File: LICENSE
Requires-Dist: numpy
Requires-Dist: carolina
Dynamic: license-file
